[{"_path":"/plugins/avg","_dir":"plugins","_draft":false,"_partial":false,"_locale":"en","_empty":false,"title":"avg - Anti-Virus scanner plugin for Haraka","description":"Haraka avg plugin - Anti-Virus scanner","navigation":{"title":"avg"},"_type":"markdown","_id":"content:8.plugins:avg.md","_source":"content","_file":"8.plugins/avg.md","_extension":"md"},{"_path":"/plugins/block_me","_dir":"plugins","_draft":false,"_partial":false,"_locale":"en","_empty":false,"title":"block_me - Block Me plugin for Haraka","description":"Haraka block_me plugin - Blocks mail from a specific IP address","navigation":{"title":"block_me"},"_type":"markdown","_id":"content:8.plugins:block_me.md","_source":"content","_file":"8.plugins/block_me.md","_extension":"md"}]