[{"_path":"/plugins/dcc","_dir":"plugins","_draft":false,"_partial":false,"_locale":"","title":"dcc - DCC plugin for Haraka","description":"Haraka dcc plugin - DCC","navigation":{"title":"dcc"},"_type":"markdown","_id":"content:8.plugins:dcc.md","_source":"content","_file":"8.plugins/dcc.md","_stem":"8.plugins/dcc","_extension":"md"},{"_path":"/plugins/dkim","_dir":"plugins","_draft":false,"_partial":false,"_locale":"","title":"dkim - DKIM plugin for Haraka","description":"Haraka DKIM plugin","navigation":{"title":"dkim"},"_type":"markdown","_id":"content:8.plugins:dkim.md","_source":"content","_file":"8.plugins/dkim.md","_stem":"8.plugins/dkim","_extension":"md"}]